setup.py
shadowsocks_extension/__init__.py
shadowsocks_extension/sspatch.py
shadowsocks_extension/test_route.py
x_mroy_1050.egg-info/PKG-INFO
x_mroy_1050.egg-info/SOURCES.txt
x_mroy_1050.egg-info/dependency_links.txt
x_mroy_1050.egg-info/entry_points.txt
x_mroy_1050.egg-info/not-zip-safe
x_mroy_1050.egg-info/requires.txt
x_mroy_1050.egg-info/top_level.txt